passacre-1.0.0.dist-info/METADATA
passacre-1.0.0.dist-info/WHEEL
passacre-1.0.0.dist-info/entry_points.txt
passacre-1.0.0.dist-info/license_files/COPYING
passacre/yaml2sqlite.py
passacre/_ordereddict.py
passacre/jsonmini.parsley
passacre/config.py
passacre/compat.py
passacre/test/test_generator.py
passacre/test/__init__.py
passacre/test/test_schema.py
passacre/test/test_multibase.py
passacre/test/test_compat.py
passacre/test/test_config.py
passacre/test/test_application.py
passacre/test/test_jsonmini.py
passacre/test/data/words
passacre/test/data/always-confirm.sqlite
passacre/test/data/nonextant-words.sqlite
passacre/test/data/no-words.sqlite
passacre/test/data/skein-yaml/words
passacre/test/data/skein-yaml/.passacre.yaml
passacre/test/data/keccak-yaml/words
passacre/test/data/keccak-yaml/.passacre.yaml
passacre/test/data/skein.yaml
passacre/test/data/keccak.yaml
passacre/test/data/json/fail7.jtest
passacre/test/data/json/fail5.jtest
passacre/test/data/json/fail21.jtest
passacre/test/data/json/fail25.jtest
passacre/test/data/json/fail27.jtest
passacre/test/data/json/fail20.jtest
passacre/test/data/json/fail4.jtest
passacre/test/data/json/fail6.jtest
passacre/test/data/json/fail22.jtest
passacre/test/data/json/fail2.jtest
passacre/test/data/json/fail26.jtest
passacre/test/data/json/fail24.jtest
passacre/test/data/json/fail19.jtest
passacre/test/data/json/pass3.jtest
passacre/test/data/json/fail15.jtest
passacre/test/data/json/fail28.jtest
passacre/test/data/json/fail33.jtest
passacre/test/data/json/pass1.jtest
passacre/test/data/json/fail17.jtest
passacre/test/data/json/fail13.jtest
passacre/test/data/json/fail8.jtest
passacre/test/data/json/fail11.jtest
passacre/test/data/json/fail32.jtest
passacre/test/data/json/fail16.jtest
passacre/test/data/json/fail14.jtest
passacre/test/data/json/pass2.jtest
passacre/test/data/json/fail9.jtest
passacre/test/data/json/fail10.jtest
passacre/test/data/json/fail12.jtest
passacre/test/data/skein-sqlite/words
passacre/test/data/skein-sqlite/.passacre.sqlite
passacre/test/data/keccak.sqlite
passacre/test/data/always-hash.sqlite
passacre/test/data/words2
passacre-1.0.0.dist-info/RECORD
