Metadata-Version: 2.3
Name: passacre
Version: 1.0.0
Classifier: Development Status :: 2 - Pre-Alpha
Classifier: Environment :: Console
Classifier: Intended Audience :: End Users/Desktop
Classifier: License :: OSI Approved :: ISC License (ISCL)
Classifier: Operating System :: OS Independent
Classifier: Topic :: Security
Classifier: Topic :: Software Development :: Libraries
Classifier: Topic :: Software Development :: Libraries :: Python Modules
Classifier: Programming Language :: Rust
Classifier: Programming Language :: Python :: Implementation :: CPython
Classifier: Programming Language :: Python :: Implementation :: PyPy
Requires-Dist: pyyaml ; extra == 'yaml'
Requires-Dist: xerox ; extra == 'clipboard'
Requires-Dist: ykpers-cffi ; extra == 'yubikey'
Requires-Dist: pyyaml ; extra == 'all'
Requires-Dist: xerox ; extra == 'all'
Requires-Dist: ykpers-cffi ; extra == 'all'
Provides-Extra: yaml
Provides-Extra: clipboard
Provides-Extra: keccak
Provides-Extra: skein
Provides-Extra: yubikey
Provides-Extra: all
License-File: COPYING
Summary: better repeatable password generation
Author-email: hab <_@habnab.it>
Requires-Python: >=3.7
Project-URL: Homepage, https://github.com/habnabit/passacre
Project-URL: Repository, https://github.com/habnabit/passacre
